data/github/venv-aa/etc/pyfrbcatdb/dbase.config
pyfrbcatdb/FRBCat.py
pyfrbcatdb/__init__.py
pyfrbcatdb/create_VOEvent.py
pyfrbcatdb/dbase.py
pyfrbcatdb/decode_VOEvent.py
pyfrbcatdb/logger.py
pyfrbcatdb/mapping.json
pyfrbcatdb/writeCSV.py
pyfrbcatdb-1.1.0.data/scripts/create_VOEvent
pyfrbcatdb-1.1.0.data/scripts/decode_VOEvent
pyfrbcatdb-1.1.0.data/scripts/frbcatdb-image
pyfrbcatdb-1.1.0.dist-info/DESCRIPTION.rst
pyfrbcatdb-1.1.0.dist-info/METADATA
pyfrbcatdb-1.1.0.dist-info/RECORD
pyfrbcatdb-1.1.0.dist-info/WHEEL
pyfrbcatdb-1.1.0.dist-info/metadata.json
pyfrbcatdb-1.1.0.dist-info/top_level.txt
