Metadata-Version: 2.0
Name: pyfrbcatdb
Version: 1.1.0
Summary: A package for manipulating the frbcatdb and its linking with the VOEvent backbone.
Home-page: https://github.com/AA-ALERT/frbcatdb
Author: Ronald van Haren, Oscar Martinez-Rubi
Author-email: r.vanharen@esciencecenter.nl
License: Apache 2.0
Keywords: VOEvent,FRBCAT
Platform: UNKNOWN
Classifier: Development Status :: 5 - Production/Stable
Classifier: Topic :: Scientific/Engineering :: Astronomy
Classifier: License :: OSI Approved :: Apache Software License
Requires-Dist: voevent-parse
Requires-Dist: python-dateutil
Requires-Dist: psycopg2
Requires-Dist: configargparse
Requires-Dist: PyYAML
Requires-Dist: astropy
